boss_bus/__init__.py
boss_bus/__main__.py
boss_bus/_utils/__init__.py
boss_bus/_utils/typing.py
boss_bus/command_bus.py
boss_bus/event_bus.py
boss_bus/handler.py
boss_bus/interface.py
boss_bus/loader/__init__.py
boss_bus/loader/instantiator.py
boss_bus/loader/lagom_loader.py
boss_bus/message_bus.py
boss_bus/middleware/__init__.py
boss_bus/middleware/log.py
boss_bus/middleware/middleware.py
boss_bus/py.typed
boss_bus-0.4.0.dist-info/LICENSE
boss_bus-0.4.0.dist-info/METADATA
boss_bus-0.4.0.dist-info/WHEEL
boss_bus-0.4.0.dist-info/entry_points.txt
boss_bus-0.4.0.dist-info/RECORD
