Metadata-Version: 2.1
Name: boss-bus
Version: 0.4.0
Summary: A Type-driven Message Bus for Python 3.8+
Home-page: https://github.com/jimbroze/boss-bus
License: GPL-3.0
Author: Jim Dickinson
Author-email: james.n.dickinson@gmail.com
Requires-Python: >=3.8.1,<4.0.0
Classifier: Development Status :: 2 - Pre-Alpha
Classifier: License :: OSI Approved :: GNU General Public License v3 (GPLv3)
Classifier: Programming Language :: Python :: 3
Classifier: Programming Language :: Python :: 3.9
Classifier: Programming Language :: Python :: 3.10
Classifier: Programming Language :: Python :: 3.11
Classifier: Programming Language :: Python :: 3.10
Classifier: Programming Language :: Python :: 3.11
Classifier: Programming Language :: Python :: 3.12
Classifier: Programming Language :: Python :: 3.8
Classifier: Programming Language :: Python :: 3.9
Classifier: Topic :: Software Development :: Libraries
Classifier: Typing :: Typed
Provides-Extra: lagom
Requires-Dist: click (>=8.0.1)
Requires-Dist: lagom (>=2.4,<3.0) ; extra == "lagom"
Requires-Dist: typeguard (>=2.13.3)
Project-URL: Changelog, https://github.com/jimbroze/boss-bus/releases
Project-URL: Documentation, https://boss-bus.readthedocs.io
Project-URL: Repository, https://github.com/jimbroze/boss-bus
